myrecorder/__init__.py
myrecorder/frontend/build/asset-manifest.json
myrecorder/frontend/build/bootstrap.min.css
myrecorder/frontend/build/index.html
myrecorder/frontend/build/static/css/main.bcba4f02.css
myrecorder/frontend/build/static/css/main.bcba4f02.css.map
myrecorder/frontend/build/static/js/main.010058c4.js
myrecorder/frontend/build/static/js/main.010058c4.js.LICENSE.txt
myrecorder/frontend/build/static/js/main.010058c4.js.map
myrecorder-0.0.0.6rc0.dist-info/LICENSE
myrecorder-0.0.0.6rc0.dist-info/METADATA
myrecorder-0.0.0.6rc0.dist-info/WHEEL
myrecorder-0.0.0.6rc0.dist-info/top_level.txt
myrecorder-0.0.0.6rc0.dist-info/RECORD
